pytest_sftpserver/__init__.py
pytest_sftpserver/autolog.py
pytest_sftpserver/compat.py
pytest_sftpserver/consts.py
pytest_sftpserver/plugin.py
pytest_sftpserver/sftp_old.py
pytest_sftpserver/keys/sftp_server.priv
pytest_sftpserver/keys/sftp_server.pub
pytest_sftpserver/sftp/__init__.py
pytest_sftpserver/sftp/content_provider.py
pytest_sftpserver/sftp/interface.py
pytest_sftpserver/sftp/server.py
pytest_sftpserver/sftp/util.py
pytest_sftpserver/sftp/virtual_sftp.py
pytest_sftpserver-1.3.0.dist-info/LICENSE
pytest_sftpserver-1.3.0.dist-info/METADATA
pytest_sftpserver-1.3.0.dist-info/WHEEL
pytest_sftpserver-1.3.0.dist-info/entry_points.txt
pytest_sftpserver-1.3.0.dist-info/top_level.txt
pytest_sftpserver-1.3.0.dist-info/RECORD
