Metadata-Version: 2.1
Name: pytest-sftpserver
Version: 1.3.0
Summary: py.test plugin to locally test sftp server connections.
Home-page: http://github.com/ulope/pytest-sftpserver/
Author: Ulrich Petri
Author-email: mail@ulo.pe
License: MIT License
Keywords: py.test pytest plugin server local sftp localhost
Platform: UNKNOWN
Classifier: Operating System :: OS Independent
Classifier: Development Status :: 4 - Beta
Classifier: Intended Audience :: Developers
Classifier: License :: OSI Approved :: MIT License
Classifier: Programming Language :: Python :: 2.7
Classifier: Programming Language :: Python :: 3.5
Classifier: Programming Language :: Python :: 3.6
Classifier: Programming Language :: Python :: 3.7
Classifier: Topic :: Software Development :: Testing
Requires-Dist: paramiko
Requires-Dist: six
